{
    "errors": [
        "EXIT_CODE_5"
    ],
    "fails": [],
    "findings": [
        {
            "confidence": "High",
            "contract": "Map",
            "filename": "dataset/access_control/mapping_write.sol",
            "function": "withdraw",
            "impact": "High",
            "line": 12,
            "message": "Map.owner (mapping_write.sol#12) is never initialized. It is used in:\n\t- withdraw (mapping_write.sol#26-29)\n",
            "name": "uninitialized-state"
        },
        {
            "confidence": "High",
            "filename": "dataset/access_control/mapping_write.sol",
            "impact": "Informational",
            "line": 12,
            "message": "Map.owner should be constant (mapping_write.sol#12)\n",
            "name": "constable-states"
        },
        {
            "confidence": "High",
            "contract": "Map",
            "filename": "dataset/access_control/mapping_write.sol",
            "function": "set",
            "impact": "Informational",
            "line": 15,
            "line_end": 21,
            "message": "Map.set (mapping_write.sol#15-21) should be declared external\n",
            "name": "external-function"
        },
        {
            "confidence": "High",
            "contract": "Map",
            "filename": "dataset/access_control/mapping_write.sol",
            "function": "get",
            "impact": "Informational",
            "line": 23,
            "line_end": 25,
            "message": "Map.get (mapping_write.sol#23-25) should be declared external\n",
            "name": "external-function"
        },
        {
            "confidence": "High",
            "contract": "Map",
            "filename": "dataset/access_control/mapping_write.sol",
            "function": "withdraw",
            "impact": "Informational",
            "line": 26,
            "line_end": 29,
            "message": "Map.withdraw (mapping_write.sol#26-29) should be declared external\n",
            "name": "external-function"
        }
    ],
    "infos": [],
    "parser": {
        "id": "slither",
        "mode": "solidity",
        "version": "2022/11/14"
    }
}
