{
    "docker": {
        "command": null,
        "detach": true,
        "entrypoint": "'/sb/bin/do_solidity' '/sb/rubixi.sol' '1800' '/sb/bin'",
        "image": "smartbugs/slither",
        "user": 0,
        "volumes": {
            "/tmp/tmpmfnn1gxx": {
                "bind": "/sb",
                "mode": "rw"
            }
        }
    },
    "filename": "dataset/access_control/rubixi.sol",
    "platform": {
        "cpu": "Common KVM processor",
        "python": "3.8.10.final.0 (64 bit)",
        "release": "5.4.0-136-generic",
        "smartbugs": "2.0.2",
        "system": "Linux",
        "version": "#153-Ubuntu SMP Thu Nov 24 15:56:58 UTC 2022"
    },
    "result": {
        "duration": 35.40990209579468,
        "exit_code": 29,
        "logs": "result.log",
        "output": "result.tar",
        "start": 1674006328.505102
    },
    "runid": "curated",
    "solc": "0.4.26",
    "tool": {
        "bin": "scripts",
        "command": null,
        "cpu_quota": null,
        "entrypoint": "'$BIN/do_solidity' '$FILENAME' '$TIMEOUT' '$BIN'",
        "id": "slither",
        "image": "smartbugs/slither",
        "info": "Slither is a Solidity static analysis framework written in Python 3. It runs a suite of vulnerability detectors and prints visual information about contract details. Slither enables developers to find vulnerabilities, enhance their code comphrehension, and quickly prototype custom analyses.",
        "mem_limit": null,
        "mode": "solidity",
        "name": "Slither",
        "origin": "https://github.com/crytic/slither",
        "output": "/output.json",
        "parser": "parser.py",
        "solc": true,
        "version": null
    }
}
