{
    "errors": [
        "EXIT_CODE_1"
    ],
    "fails": [],
    "findings": [
        {
            "column": 2,
            "filename": "dataset/unchecked_low_level_calls/0xf70d589d76eebdd7c12cc5eec99f8f6fa4233b9e.sol",
            "level": "error",
            "line": 25,
            "message": "Line length must be no more than 120 but current length is 5333.",
            "name": "max-line-length"
        },
        {
            "column": 3470,
            "filename": "dataset/unchecked_low_level_calls/0xf70d589d76eebdd7c12cc5eec99f8f6fa4233b9e.sol",
            "level": "error",
            "line": 25,
            "message": "Expected indentation of 12 spaces but found 3469",
            "name": "indent"
        },
        {
            "column": 2,
            "filename": "dataset/unchecked_low_level_calls/0xf70d589d76eebdd7c12cc5eec99f8f6fa4233b9e.sol",
            "level": "error",
            "line": 27,
            "message": "Line length must be no more than 120 but current length is 121.",
            "name": "max-line-length"
        },
        {
            "column": 2,
            "filename": "dataset/unchecked_low_level_calls/0xf70d589d76eebdd7c12cc5eec99f8f6fa4233b9e.sol",
            "level": "error",
            "line": 33,
            "message": "Line length must be no more than 120 but current length is 3116.",
            "name": "max-line-length"
        },
        {
            "column": 1198,
            "filename": "dataset/unchecked_low_level_calls/0xf70d589d76eebdd7c12cc5eec99f8f6fa4233b9e.sol",
            "level": "error",
            "line": 33,
            "message": "Expected indentation of 8 spaces but found 1197",
            "name": "indent"
        }
    ],
    "infos": [],
    "parser": {
        "id": "solhint",
        "mode": "solidity",
        "version": "2022/11/14"
    }
}
