{
    "errors": [],
    "fails": [],
    "findings": [
        {
            "contract": "Government",
            "filename": "dataset/denial_of_service/list_dos.sol",
            "name": "Not destructible (no self-destruct)"
        },
        {
            "contract": "Government",
            "filename": "dataset/denial_of_service/list_dos.sol",
            "name": "No Ether lock (Ether refused)"
        }
    ],
    "infos": [],
    "parser": {
        "id": "maian",
        "mode": "solidity",
        "version": "2022/11/11"
    }
}
