{
    "errors": [],
    "fails": [],
    "findings": [
        {
            "column": 26,
            "filename": "dataset/reentrancy/0xbe4041d55db380c5ae9d4a9b9703f1ed4e7e3888.sol",
            "line": 63,
            "name": "SOLIDITY_CALL_WITHOUT_DATA",
            "severity": 2
        },
        {
            "column": 23,
            "filename": "dataset/reentrancy/0xbe4041d55db380c5ae9d4a9b9703f1ed4e7e3888.sol",
            "line": 28,
            "name": "SOLIDITY_DEPRECATED_CONSTRUCTIONS",
            "severity": 1
        },
        {
            "column": 23,
            "filename": "dataset/reentrancy/0xbe4041d55db380c5ae9d4a9b9703f1ed4e7e3888.sol",
            "line": 35,
            "name": "SOLIDITY_DEPRECATED_CONSTRUCTIONS",
            "severity": 1
        },
        {
            "column": 16,
            "filename": "dataset/reentrancy/0xbe4041d55db380c5ae9d4a9b9703f1ed4e7e3888.sol",
            "line": 7,
            "name": "SOLIDITY_PRAGMAS_VERSION",
            "severity": 1
        },
        {
            "column": 8,
            "filename": "dataset/reentrancy/0xbe4041d55db380c5ae9d4a9b9703f1ed4e7e3888.sol",
            "line": 28,
            "name": "SOLIDITY_REVERT_REQUIRE",
            "severity": 1
        },
        {
            "column": 8,
            "filename": "dataset/reentrancy/0xbe4041d55db380c5ae9d4a9b9703f1ed4e7e3888.sol",
            "line": 35,
            "name": "SOLIDITY_REVERT_REQUIRE",
            "severity": 1
        },
        {
            "column": 26,
            "filename": "dataset/reentrancy/0xbe4041d55db380c5ae9d4a9b9703f1ed4e7e3888.sol",
            "line": 63,
            "name": "SOLIDITY_UPGRADE_TO_050",
            "severity": 1
        },
        {
            "column": 4,
            "filename": "dataset/reentrancy/0xbe4041d55db380c5ae9d4a9b9703f1ed4e7e3888.sol",
            "line": 72,
            "name": "SOLIDITY_UPGRADE_TO_050",
            "severity": 1
        },
        {
            "column": 47,
            "filename": "dataset/reentrancy/0xbe4041d55db380c5ae9d4a9b9703f1ed4e7e3888.sol",
            "line": 95,
            "name": "SOLIDITY_UPGRADE_TO_050",
            "severity": 1
        },
        {
            "column": 4,
            "filename": "dataset/reentrancy/0xbe4041d55db380c5ae9d4a9b9703f1ed4e7e3888.sol",
            "line": 21,
            "name": "SOLIDITY_VISIBILITY",
            "severity": 1
        },
        {
            "column": 4,
            "filename": "dataset/reentrancy/0xbe4041d55db380c5ae9d4a9b9703f1ed4e7e3888.sol",
            "line": 23,
            "name": "SOLIDITY_VISIBILITY",
            "severity": 1
        },
        {
            "column": 4,
            "filename": "dataset/reentrancy/0xbe4041d55db380c5ae9d4a9b9703f1ed4e7e3888.sol",
            "line": 93,
            "name": "SOLIDITY_VISIBILITY",
            "severity": 1
        }
    ],
    "infos": [],
    "parser": {
        "id": "smartcheck",
        "mode": "solidity",
        "version": "2022/11/14"
    }
}
