{
    "errors": [],
    "fails": [],
    "findings": [
        {
            "column": 9,
            "contract": "Freebie",
            "filename": "dataset/unchecked_low_level_calls/0xe82f0742a71a02b9e9ffc142fdcb6eb1ed06fb87.sol",
            "line": 30,
            "name": "Concurrency bug"
        },
        {
            "column": 9,
            "contract": "Freebie",
            "filename": "dataset/unchecked_low_level_calls/0xe82f0742a71a02b9e9ffc142fdcb6eb1ed06fb87.sol",
            "line": 39,
            "name": "Reentrancy bug"
        }
    ],
    "infos": [],
    "parser": {
        "id": "osiris",
        "mode": "solidity",
        "version": "2022/11/11"
    }
}
