{
    "docker": {
        "command": null,
        "detach": true,
        "entrypoint": "'/sb/bin/do_solidity' '/sb/overflow_simple_add.sol' '/sb/bin'",
        "image": "smartbugs/security:usolc",
        "user": 0,
        "volumes": {
            "/tmp/tmp0wo7ly3w": {
                "bind": "/sb",
                "mode": "rw"
            }
        }
    },
    "filename": "dataset/arithmetic/overflow_simple_add.sol",
    "platform": {
        "cpu": "Common KVM processor",
        "python": "3.8.10.final.0 (64 bit)",
        "release": "5.4.0-136-generic",
        "smartbugs": "2.0.2",
        "system": "Linux",
        "version": "#153-Ubuntu SMP Thu Nov 24 15:56:58 UTC 2022"
    },
    "result": {
        "duration": 9.471054792404175,
        "exit_code": 0,
        "logs": null,
        "output": "result.tar",
        "start": 1674035158.1117373
    },
    "runid": "curated",
    "solc": "0.4.25",
    "tool": {
        "bin": "scripts",
        "command": null,
        "cpu_quota": null,
        "entrypoint": "'$BIN/do_solidity' '$FILENAME' '$BIN'",
        "id": "securify",
        "image": "smartbugs/security:usolc",
        "info": "Securify uses formal verification, also relying on static analysis checks. Securify's analysis consists of two steps. First, it symbolically analyzes the contract's dependency graph to extract precise semantic information from the code. Then, it checks compliance and violation patterns that capture sufficient conditions for proving if a property holds or not.",
        "mem_limit": null,
        "mode": "solidity",
        "name": "Securify",
        "origin": "https://github.com/eth-sri/securify",
        "output": "/results/",
        "parser": "parser.py",
        "solc": true,
        "version": null
    }
}
