{
    "errors": [
        "EXIT_CODE_1"
    ],
    "fails": [],
    "findings": [
        {
            "column": 3,
            "filename": "dataset/unchecked_low_level_calls/0x663e4229142a27f00bafb5d087e1e730648314c3.sol",
            "level": "error",
            "line": 28,
            "message": "Expected indentation of 4 spaces but found 2",
            "name": "indent"
        },
        {
            "column": 3,
            "filename": "dataset/unchecked_low_level_calls/0x663e4229142a27f00bafb5d087e1e730648314c3.sol",
            "level": "error",
            "line": 35,
            "message": "Expected indentation of 4 spaces but found 2",
            "name": "indent"
        },
        {
            "column": 5,
            "filename": "dataset/unchecked_low_level_calls/0x663e4229142a27f00bafb5d087e1e730648314c3.sol",
            "level": "error",
            "line": 36,
            "message": "Expected indentation of 8 spaces but found 4",
            "name": "indent"
        },
        {
            "column": 3,
            "filename": "dataset/unchecked_low_level_calls/0x663e4229142a27f00bafb5d087e1e730648314c3.sol",
            "level": "error",
            "line": 37,
            "message": "Expected indentation of 4 spaces but found 2",
            "name": "indent"
        },
        {
            "column": 3,
            "filename": "dataset/unchecked_low_level_calls/0x663e4229142a27f00bafb5d087e1e730648314c3.sol",
            "level": "error",
            "line": 43,
            "message": "Expected indentation of 4 spaces but found 2",
            "name": "indent"
        },
        {
            "column": 5,
            "filename": "dataset/unchecked_low_level_calls/0x663e4229142a27f00bafb5d087e1e730648314c3.sol",
            "level": "error",
            "line": 44,
            "message": "Expected indentation of 8 spaces but found 4",
            "name": "indent"
        },
        {
            "column": 5,
            "filename": "dataset/unchecked_low_level_calls/0x663e4229142a27f00bafb5d087e1e730648314c3.sol",
            "level": "error",
            "line": 45,
            "message": "Expected indentation of 8 spaces but found 4",
            "name": "indent"
        },
        {
            "column": 3,
            "filename": "dataset/unchecked_low_level_calls/0x663e4229142a27f00bafb5d087e1e730648314c3.sol",
            "level": "error",
            "line": 46,
            "message": "Expected indentation of 4 spaces but found 2",
            "name": "indent"
        },
        {
            "column": 3,
            "filename": "dataset/unchecked_low_level_calls/0x663e4229142a27f00bafb5d087e1e730648314c3.sol",
            "level": "error",
            "line": 53,
            "message": "Expected indentation of 4 spaces but found 2",
            "name": "indent"
        },
        {
            "column": 5,
            "filename": "dataset/unchecked_low_level_calls/0x663e4229142a27f00bafb5d087e1e730648314c3.sol",
            "level": "error",
            "line": 54,
            "message": "Expected indentation of 8 spaces but found 4",
            "name": "indent"
        },
        {
            "column": 7,
            "filename": "dataset/unchecked_low_level_calls/0x663e4229142a27f00bafb5d087e1e730648314c3.sol",
            "level": "error",
            "line": 55,
            "message": "Expected indentation of 12 spaces but found 6",
            "name": "indent"
        },
        {
            "column": 5,
            "filename": "dataset/unchecked_low_level_calls/0x663e4229142a27f00bafb5d087e1e730648314c3.sol",
            "level": "error",
            "line": 56,
            "message": "Expected indentation of 8 spaces but found 4",
            "name": "indent"
        },
        {
            "column": 3,
            "filename": "dataset/unchecked_low_level_calls/0x663e4229142a27f00bafb5d087e1e730648314c3.sol",
            "level": "error",
            "line": 57,
            "message": "Expected indentation of 4 spaces but found 2",
            "name": "indent"
        },
        {
            "column": 2,
            "filename": "dataset/unchecked_low_level_calls/0x663e4229142a27f00bafb5d087e1e730648314c3.sol",
            "level": "error",
            "line": 94,
            "message": "Line length must be no more than 120 but current length is 131.",
            "name": "max-line-length"
        },
        {
            "column": 2,
            "filename": "dataset/unchecked_low_level_calls/0x663e4229142a27f00bafb5d087e1e730648314c3.sol",
            "level": "error",
            "line": 818,
            "message": "Line length must be no more than 120 but current length is 180.",
            "name": "max-line-length"
        },
        {
            "column": 2,
            "filename": "dataset/unchecked_low_level_calls/0x663e4229142a27f00bafb5d087e1e730648314c3.sol",
            "level": "error",
            "line": 1116,
            "message": "Line length must be no more than 120 but current length is 151.",
            "name": "max-line-length"
        },
        {
            "column": 2,
            "filename": "dataset/unchecked_low_level_calls/0x663e4229142a27f00bafb5d087e1e730648314c3.sol",
            "level": "error",
            "line": 1122,
            "message": "Line length must be no more than 120 but current length is 134.",
            "name": "max-line-length"
        },
        {
            "column": 3,
            "filename": "dataset/unchecked_low_level_calls/0x663e4229142a27f00bafb5d087e1e730648314c3.sol",
            "level": "error",
            "line": 1417,
            "message": "Expected indentation of 4 spaces but found 2",
            "name": "indent"
        },
        {
            "column": 3,
            "filename": "dataset/unchecked_low_level_calls/0x663e4229142a27f00bafb5d087e1e730648314c3.sol",
            "level": "error",
            "line": 1418,
            "message": "Expected indentation of 4 spaces but found 2",
            "name": "indent"
        },
        {
            "column": 3,
            "filename": "dataset/unchecked_low_level_calls/0x663e4229142a27f00bafb5d087e1e730648314c3.sol",
            "level": "error",
            "line": 1420,
            "message": "Expected indentation of 4 spaces but found 2",
            "name": "indent"
        },
        {
            "column": 3,
            "filename": "dataset/unchecked_low_level_calls/0x663e4229142a27f00bafb5d087e1e730648314c3.sol",
            "level": "error",
            "line": 1426,
            "message": "Expected indentation of 4 spaces but found 2",
            "name": "indent"
        },
        {
            "column": 5,
            "filename": "dataset/unchecked_low_level_calls/0x663e4229142a27f00bafb5d087e1e730648314c3.sol",
            "level": "error",
            "line": 1427,
            "message": "Expected indentation of 8 spaces but found 4",
            "name": "indent"
        },
        {
            "column": 5,
            "filename": "dataset/unchecked_low_level_calls/0x663e4229142a27f00bafb5d087e1e730648314c3.sol",
            "level": "error",
            "line": 1428,
            "message": "Expected indentation of 8 spaces but found 4",
            "name": "indent"
        },
        {
            "column": 3,
            "filename": "dataset/unchecked_low_level_calls/0x663e4229142a27f00bafb5d087e1e730648314c3.sol",
            "level": "error",
            "line": 1429,
            "message": "Expected indentation of 4 spaces but found 2",
            "name": "indent"
        },
        {
            "column": 3,
            "filename": "dataset/unchecked_low_level_calls/0x663e4229142a27f00bafb5d087e1e730648314c3.sol",
            "level": "error",
            "line": 1434,
            "message": "Expected indentation of 4 spaces but found 2",
            "name": "indent"
        },
        {
            "column": 5,
            "filename": "dataset/unchecked_low_level_calls/0x663e4229142a27f00bafb5d087e1e730648314c3.sol",
            "level": "error",
            "line": 1435,
            "message": "Expected indentation of 8 spaces but found 4",
            "name": "indent"
        },
        {
            "column": 5,
            "filename": "dataset/unchecked_low_level_calls/0x663e4229142a27f00bafb5d087e1e730648314c3.sol",
            "level": "error",
            "line": 1436,
            "message": "Expected indentation of 8 spaces but found 4",
            "name": "indent"
        },
        {
            "column": 3,
            "filename": "dataset/unchecked_low_level_calls/0x663e4229142a27f00bafb5d087e1e730648314c3.sol",
            "level": "error",
            "line": 1437,
            "message": "Expected indentation of 4 spaces but found 2",
            "name": "indent"
        },
        {
            "column": 3,
            "filename": "dataset/unchecked_low_level_calls/0x663e4229142a27f00bafb5d087e1e730648314c3.sol",
            "level": "error",
            "line": 1442,
            "message": "Expected indentation of 4 spaces but found 2",
            "name": "indent"
        },
        {
            "column": 5,
            "filename": "dataset/unchecked_low_level_calls/0x663e4229142a27f00bafb5d087e1e730648314c3.sol",
            "level": "error",
            "line": 1443,
            "message": "Expected indentation of 8 spaces but found 4",
            "name": "indent"
        },
        {
            "column": 5,
            "filename": "dataset/unchecked_low_level_calls/0x663e4229142a27f00bafb5d087e1e730648314c3.sol",
            "level": "error",
            "line": 1444,
            "message": "Expected indentation of 8 spaces but found 4",
            "name": "indent"
        },
        {
            "column": 5,
            "filename": "dataset/unchecked_low_level_calls/0x663e4229142a27f00bafb5d087e1e730648314c3.sol",
            "level": "error",
            "line": 1445,
            "message": "Expected indentation of 8 spaces but found 4",
            "name": "indent"
        },
        {
            "column": 3,
            "filename": "dataset/unchecked_low_level_calls/0x663e4229142a27f00bafb5d087e1e730648314c3.sol",
            "level": "error",
            "line": 1446,
            "message": "Expected indentation of 4 spaces but found 2",
            "name": "indent"
        },
        {
            "column": 3,
            "filename": "dataset/unchecked_low_level_calls/0x663e4229142a27f00bafb5d087e1e730648314c3.sol",
            "level": "error",
            "line": 1451,
            "message": "Expected indentation of 4 spaces but found 2",
            "name": "indent"
        },
        {
            "column": 5,
            "filename": "dataset/unchecked_low_level_calls/0x663e4229142a27f00bafb5d087e1e730648314c3.sol",
            "level": "error",
            "line": 1452,
            "message": "Expected indentation of 8 spaces but found 4",
            "name": "indent"
        },
        {
            "column": 5,
            "filename": "dataset/unchecked_low_level_calls/0x663e4229142a27f00bafb5d087e1e730648314c3.sol",
            "level": "error",
            "line": 1453,
            "message": "Expected indentation of 8 spaces but found 4",
            "name": "indent"
        },
        {
            "column": 5,
            "filename": "dataset/unchecked_low_level_calls/0x663e4229142a27f00bafb5d087e1e730648314c3.sol",
            "level": "error",
            "line": 1454,
            "message": "Expected indentation of 8 spaces but found 4",
            "name": "indent"
        },
        {
            "column": 3,
            "filename": "dataset/unchecked_low_level_calls/0x663e4229142a27f00bafb5d087e1e730648314c3.sol",
            "level": "error",
            "line": 1455,
            "message": "Expected indentation of 4 spaces but found 2",
            "name": "indent"
        },
        {
            "column": 9,
            "filename": "dataset/unchecked_low_level_calls/0x663e4229142a27f00bafb5d087e1e730648314c3.sol",
            "level": "error",
            "line": 1590,
            "message": "Expected indentation of 12 spaces but found 8",
            "name": "indent"
        },
        {
            "column": 9,
            "filename": "dataset/unchecked_low_level_calls/0x663e4229142a27f00bafb5d087e1e730648314c3.sol",
            "level": "error",
            "line": 1591,
            "message": "Expected indentation of 12 spaces but found 8",
            "name": "indent"
        },
        {
            "column": 9,
            "filename": "dataset/unchecked_low_level_calls/0x663e4229142a27f00bafb5d087e1e730648314c3.sol",
            "level": "error",
            "line": 1592,
            "message": "Expected indentation of 12 spaces but found 8",
            "name": "indent"
        },
        {
            "column": 5,
            "filename": "dataset/unchecked_low_level_calls/0x663e4229142a27f00bafb5d087e1e730648314c3.sol",
            "level": "error",
            "line": 1599,
            "message": "Expected indentation of 8 spaces but found 4",
            "name": "indent"
        },
        {
            "column": 13,
            "filename": "dataset/unchecked_low_level_calls/0x663e4229142a27f00bafb5d087e1e730648314c3.sol",
            "level": "error",
            "line": 1708,
            "message": "Expected indentation of 8 spaces but found 12",
            "name": "indent"
        },
        {
            "column": 13,
            "filename": "dataset/unchecked_low_level_calls/0x663e4229142a27f00bafb5d087e1e730648314c3.sol",
            "level": "error",
            "line": 1709,
            "message": "Expected indentation of 8 spaces but found 12",
            "name": "indent"
        },
        {
            "column": 2,
            "filename": "dataset/unchecked_low_level_calls/0x663e4229142a27f00bafb5d087e1e730648314c3.sol",
            "level": "error",
            "line": 1845,
            "message": "Line length must be no more than 120 but current length is 132.",
            "name": "max-line-length"
        },
        {
            "column": 5,
            "filename": "dataset/unchecked_low_level_calls/0x663e4229142a27f00bafb5d087e1e730648314c3.sol",
            "level": "error",
            "line": 1931,
            "message": "Expected indentation of 8 spaces but found 4",
            "name": "indent"
        },
        {
            "column": 2,
            "filename": "dataset/unchecked_low_level_calls/0x663e4229142a27f00bafb5d087e1e730648314c3.sol",
            "level": "error",
            "line": 2035,
            "message": "Line length must be no more than 120 but current length is 180.",
            "name": "max-line-length"
        },
        {
            "column": 2,
            "filename": "dataset/unchecked_low_level_calls/0x663e4229142a27f00bafb5d087e1e730648314c3.sol",
            "level": "error",
            "line": 2045,
            "message": "Line length must be no more than 120 but current length is 180.",
            "name": "max-line-length"
        },
        {
            "column": 2,
            "filename": "dataset/unchecked_low_level_calls/0x663e4229142a27f00bafb5d087e1e730648314c3.sol",
            "level": "error",
            "line": 2057,
            "message": "Line length must be no more than 120 but current length is 180.",
            "name": "max-line-length"
        },
        {
            "column": 8,
            "filename": "dataset/unchecked_low_level_calls/0x663e4229142a27f00bafb5d087e1e730648314c3.sol",
            "level": "error",
            "line": 2386,
            "message": "Expected indentation of 8 spaces but found 7",
            "name": "indent"
        },
        {
            "column": 9,
            "filename": "dataset/unchecked_low_level_calls/0x663e4229142a27f00bafb5d087e1e730648314c3.sol",
            "level": "error",
            "line": 2429,
            "message": "Expected indentation of 12 spaces but found 8",
            "name": "indent"
        },
        {
            "column": 9,
            "filename": "dataset/unchecked_low_level_calls/0x663e4229142a27f00bafb5d087e1e730648314c3.sol",
            "level": "error",
            "line": 2432,
            "message": "Expected indentation of 12 spaces but found 8",
            "name": "indent"
        },
        {
            "column": 9,
            "filename": "dataset/unchecked_low_level_calls/0x663e4229142a27f00bafb5d087e1e730648314c3.sol",
            "level": "error",
            "line": 2433,
            "message": "Expected indentation of 12 spaces but found 8",
            "name": "indent"
        },
        {
            "column": 9,
            "filename": "dataset/unchecked_low_level_calls/0x663e4229142a27f00bafb5d087e1e730648314c3.sol",
            "level": "error",
            "line": 2434,
            "message": "Expected indentation of 12 spaces but found 8",
            "name": "indent"
        },
        {
            "column": 9,
            "filename": "dataset/unchecked_low_level_calls/0x663e4229142a27f00bafb5d087e1e730648314c3.sol",
            "level": "error",
            "line": 2435,
            "message": "Expected indentation of 12 spaces but found 8",
            "name": "indent"
        },
        {
            "column": 9,
            "filename": "dataset/unchecked_low_level_calls/0x663e4229142a27f00bafb5d087e1e730648314c3.sol",
            "level": "error",
            "line": 2436,
            "message": "Expected indentation of 12 spaces but found 8",
            "name": "indent"
        },
        {
            "column": 9,
            "filename": "dataset/unchecked_low_level_calls/0x663e4229142a27f00bafb5d087e1e730648314c3.sol",
            "level": "error",
            "line": 2437,
            "message": "Expected indentation of 12 spaces but found 8",
            "name": "indent"
        },
        {
            "column": 9,
            "filename": "dataset/unchecked_low_level_calls/0x663e4229142a27f00bafb5d087e1e730648314c3.sol",
            "level": "error",
            "line": 2438,
            "message": "Expected indentation of 12 spaces but found 8",
            "name": "indent"
        },
        {
            "column": 9,
            "filename": "dataset/unchecked_low_level_calls/0x663e4229142a27f00bafb5d087e1e730648314c3.sol",
            "level": "error",
            "line": 2439,
            "message": "Expected indentation of 12 spaces but found 8",
            "name": "indent"
        },
        {
            "column": 9,
            "filename": "dataset/unchecked_low_level_calls/0x663e4229142a27f00bafb5d087e1e730648314c3.sol",
            "level": "error",
            "line": 2440,
            "message": "Expected indentation of 12 spaces but found 8",
            "name": "indent"
        },
        {
            "column": 9,
            "filename": "dataset/unchecked_low_level_calls/0x663e4229142a27f00bafb5d087e1e730648314c3.sol",
            "level": "error",
            "line": 2441,
            "message": "Expected indentation of 12 spaces but found 8",
            "name": "indent"
        },
        {
            "column": 5,
            "filename": "dataset/unchecked_low_level_calls/0x663e4229142a27f00bafb5d087e1e730648314c3.sol",
            "level": "error",
            "line": 2442,
            "message": "Expected indentation of 8 spaces but found 4",
            "name": "indent"
        }
    ],
    "infos": [],
    "parser": {
        "id": "solhint",
        "mode": "solidity",
        "version": "2022/11/14"
    }
}
